keepass_env.py
keepass_env-0.1.3.dist-info/METADATA
keepass_env-0.1.3.dist-info/WHEEL
keepass_env-0.1.3.dist-info/entry_points.txt
keepass_env-0.1.3.dist-info/top_level.txt
keepass_env-0.1.3.dist-info/RECORD
