Metadata-Version: 2.1
Name: keepass-env
Version: 0.1.3
Summary: read key-value pairs from a .kdbx file and set them as environment variables or return as dict
Author-email: Alexander Rodionov <tandav@tandav.me>
Project-URL: source, https://github.com/tandav/keepass-env
Project-URL: docs, https://tandav.github.io/keepass-env/
Project-URL: issues, https://github.com/tandav/keepass-env/issues
Project-URL: release notes, https://github.com/tandav/keepass-env/releases
Requires-Python: >=3.10
Requires-Dist: pykeepass
Provides-Extra: dev
Requires-Dist: bumpver ; extra == 'dev'
Requires-Dist: pre-commit ; extra == 'dev'
Requires-Dist: pytest ; extra == 'dev'
Requires-Dist: pytest-cov ; extra == 'dev'
Requires-Dist: mkdocs ; extra == 'dev'
Requires-Dist: mkdocs-material ; extra == 'dev'
